esa_swesnet_client/__init__.py
esa_swesnet_client/core.py
esa_swesnet_client-0.1.12.dist-info/METADATA
esa_swesnet_client-0.1.12.dist-info/WHEEL
esa_swesnet_client-0.1.12.dist-info/RECORD
